jhidatabricksenv/__init__.py
JHI_DatabricksEnvironment-0.1.dist-info/LICENSE
JHI_DatabricksEnvironment-0.1.dist-info/METADATA
JHI_DatabricksEnvironment-0.1.dist-info/WHEEL
JHI_DatabricksEnvironment-0.1.dist-info/top_level.txt
JHI_DatabricksEnvironment-0.1.dist-info/RECORD
