Metadata-Version: 2.1
Name: JHI-DatabricksEnvironment
Version: 0.1
Summary: JHI Databricks Environment Package
Home-page: https://github.com/pypa/JHI-DatabricksEnvironment
Author: Core Cloud Platform Team
Author-email: CoreCloudPlatform@janushenderson.com
License: UNKNOWN
Project-URL: Bug Tracker, https://github.com/pypa/JHI-DatabricksEnvironment/issues
Platform: UNKNOWN
Classifier: Programming Language :: Python :: 3
Classifier: License :: OSI Approved :: MIT License
Classifier: Operating System :: OS Independent
Requires-Python: >=3.6
